pyvtools/__init__.py
pyvtools/algebra.py
pyvtools/image.py
pyvtools/text.py
pyvtools/tests/__init__.py
pyvtools/tests/test_image.py
pyvtools-1.3.1.dist-info/licenses/LICENSE
pyvtools-1.3.1.dist-info/METADATA
pyvtools-1.3.1.dist-info/WHEEL
pyvtools-1.3.1.dist-info/top_level.txt
pyvtools-1.3.1.dist-info/RECORD
