Metadata-Version: 2.4
Name: pyvtools
Version: 1.3.1
Summary: Python tools
Author-email: Valeria Pais <valeriarpais@gmail.com>
License: MIT License
Project-URL: Repository, https://github.com/0xInfty/PyVTools.git
Project-URL: Homepage, https://github.com/0xInfty/PyVTools
Project-URL: Issues, https://github.com/0xInfty/PyVTools/issues
Keywords: deep learning,pytorch
Classifier: Development Status :: 3 - Alpha
Classifier: License :: OSI Approved :: MIT License
Classifier: Programming Language :: Python :: 3
Requires-Python: >=3.8.0
License-File: LICENSE
Requires-Dist: numpy
Requires-Dist: matplotlib
Requires-Dist: opencv-python
Requires-Dist: scikit-image
Requires-Dist: pillow
Requires-Dist: scikit-learn
Requires-Dist: tifffile
Dynamic: license-file
